mylearn/__init__.py
mylearn-0.0.3.dist-info/LICENSE
mylearn-0.0.3.dist-info/METADATA
mylearn-0.0.3.dist-info/WHEEL
mylearn-0.0.3.dist-info/RECORD
