Metadata-Version: 2.1
Name: mylearn
Version: 0.0.3
Summary: mylearn: my Machine Learning framework
Home-page: https://github.com/MichaelKarpe/mylearn
License: MIT
Keywords: airflow,mlflow
Author: Michael Karpe
Author-email: michael.karpe@berkeley.edu
Requires-Python: >=3.8,<3.12
Classifier: License :: OSI Approved :: MIT License
Classifier: Programming Language :: Python :: 3
Classifier: Programming Language :: Python :: 3.8
Classifier: Programming Language :: Python :: 3.9
Classifier: Programming Language :: Python :: 3.10
Classifier: Programming Language :: Python :: 3.11
Classifier: Programming Language :: Python :: 3.10
Classifier: Programming Language :: Python :: 3.11
Classifier: Programming Language :: Python :: 3.8
Classifier: Programming Language :: Python :: 3.9
Requires-Dist: apache-airflow[postgres] (>=2.5.3,<3.0.0)
Requires-Dist: llvmlite (>=0.40.0rc1,<0.41.0)
Requires-Dist: mlflow[pipelines] (>=2.2.2,<3.0.0)
Requires-Dist: numba (>=0.57.0rc1,<0.58.0)
Requires-Dist: pandas (>=1.5.3,<2.0.0)
Requires-Dist: polars (>=0.17.3,<0.18.0)
Requires-Dist: psycopg2 (>=2.9.5,<3.0.0)
Project-URL: Repository, https://github.com/MichaelKarpe/mylearn
